synth/__init__.py
synth/setup.py
synth/synth.py
synth/__pycache__/synth.cpython-37.pyc
synth/build/lib/part_builder/__init__.py
synth/build/lib/part_builder/part_builder.py
synth/build/lib/part_builder/part_exception.py
synth/build/lib/synth_part_builder/__init__.py
synth/build/lib/synth_part_builder/part_builder.py
synth/build/lib/synth_part_builder/part_exception.py
synth/dist/synth_part_builder-1.1-py3-none-any.whl
synth/dist/synth_part_builder-1.1-py3.7.egg
synth/dist/synth_part_builder-1.1.tar.gz
synth/part_builder/__init__.py
synth/part_builder/part_builder.py
synth/part_builder/part_exception.py
synth/part_builder/__pycache__/__init__.cpython-37.pyc
synth/part_builder/__pycache__/part_builder.cpython-37.pyc
synth/part_builder/__pycache__/part_exception.cpython-37.pyc
synth/parts/compose/django.part
synth/parts/compose/dynamic.part
synth/parts/compose/flask.part
synth/parts/compose/mariadb.part
synth/parts/compose/memcached.part
synth/parts/compose/mongo.part
synth/parts/compose/mysql.part
synth/parts/compose/node.part
synth/parts/compose/postgres.part
synth/parts/compose/react.part
synth/parts/compose/redis.part
synth/parts/compose/static.part
synth/parts/compose/depends/backend.part
synth/parts/compose/depends/base.part
synth/parts/compose/depends/frontend.part
synth/parts/compose/depends/mariadb.part
synth/parts/compose/depends/memcached.part
synth/parts/compose/depends/mongo.part
synth/parts/compose/depends/mysql.part
synth/parts/compose/depends/postgres.part
synth/parts/compose/depends/redis.part
synth/parts/compose/env/base.part
synth/parts/compose/env/mariadb.part
synth/parts/compose/env/memcached.part
synth/parts/compose/env/mongo.part
synth/parts/compose/env/mysql.part
synth/parts/compose/env/postgres.part
synth/parts/compose/env/redis.part
synth/parts/nginx/location/django.part
synth/parts/nginx/location/dynamic.part
synth/parts/nginx/location/flask.part
synth/parts/nginx/location/node.part
synth/parts/nginx/location/react.part
synth/synth_part_builder.egg-info/PKG-INFO
synth/synth_part_builder.egg-info/SOURCES.txt
synth/synth_part_builder.egg-info/dependency_links.txt
synth/synth_part_builder.egg-info/top_level.txt
boot_synth-1.1.1.dist-info/AUTHORS
boot_synth-1.1.1.dist-info/LICENSE.txt
boot_synth-1.1.1.dist-info/METADATA
boot_synth-1.1.1.dist-info/WHEEL
boot_synth-1.1.1.dist-info/entry_points.txt
boot_synth-1.1.1.dist-info/top_level.txt
boot_synth-1.1.1.dist-info/RECORD
