Metadata-Version: 2.1
Name: boot-synth
Version: 1.1.1
Summary: Synth: a docker bootstrapping CLI tool
Home-page: UNKNOWN
Author: Bennett Dixon, Jack Gindi
Author-email: bennettdixon16@gmail.com, jmgindi@gmail.com
License: MIT
Platform: UNKNOWN
Requires-Dist: click
Requires-Dist: synth-part-builder
